{"language": "en-US", "region": "US", "quoteType": "FUTURE", "contractSymbol": false, "headSymbolAsString": "PA=F", "currency": "USD", "exchangeDataDelayedBy": 30, "market": "us24_market", "bidSize": 18, "askSize": 8, "fullExchangeName": "NY Mercantile", "averageDailyVolume3Month": 624666, "averageDailyVolume10Day": 890249, "regularMarketPreviousClose": 1405.2, "marketState": "REGULAR", "priceHint": 2, "shortName": "Palladium Dec 19", "regularMarketChangePercent": -0.6053269, "ask": 1397.0, "bid": 1395.3, "fiftyDayAverage": 1483.0814, "fiftyDayAverageChange": -87.38147, "fiftyDayAverageChangePercent": -0.058918864, "twoHundredDayAverage": 1412.6812, "twoHundredDayAverageChange": -16.981201, "twoHundredDayAverageChangePercent": -0.012020548, "exchange": "NYM", "regularMarketDayRange": "1390.0 - 1418.5", "esgPopulated": false, "tradeable": false, "triggerable": false, "expireDate": 1577404800, "expireIsoDate": "2019-12-27T00:00:00Z", "regularMarketPrice": 1395.7, "regularMarketTime": 1564996789, "regularMarketChange": -8.5, "regularMarketOpen": 1398.0, "regularMarketDayHigh": 1418.5, "regularMarketDayLow": 1390.0, "regularMarketVolume": 885, "sourceInterval": 30, "exchangeTimezoneName": "America/New_York", "exchangeTimezoneShortName": "EDT", "gmtOffSetMilliseconds": -14400000, "fiftyTwoWeekLowChange": 1395.7, "fiftyTwoWeekRange": "0.0 - 1600.5", "fiftyTwoWeekHighChange": -204.80005, "fiftyTwoWeekHighChangePercent": -0.12796004, "fiftyTwoWeekLow": 0.0, "fiftyTwoWeekHigh": 1600.5, "underlyingSymbol": "PAZ19.NYM", "underlyingExchangeSymbol": "PAZ19.NYM", "openInterest": 3907, "symbol": "PA=F"}